optorch/__init__.py
optorch/debug.py
optorch/main
optorch/problem.py
optorch-0.0.4.dist-info/LICENSE
optorch-0.0.4.dist-info/METADATA
optorch-0.0.4.dist-info/WHEEL
optorch-0.0.4.dist-info/top_level.txt
optorch-0.0.4.dist-info/RECORD
