Metadata-Version: 2.1
Name: optorch
Version: 0.0.4
Summary: Nonlinear solver for PyTorch
Home-page: https://github.com/pronto-ai/optorch
Author: Pronto AI
License: MIT
Platform: UNKNOWN
Requires-Dist: torch
